{
    "Petya": {
        "interests": [
            "football",
            "ancient history",
            "Rust"
        ],
        "seat": "1C",
        "age": 18
    },
    "Vasya": {
        "interests": [
            "cooking",
            "Rust"
        ],
        "seat": "1A",
        "age": 18
    },
    "Ivan": {
        "interests": [
            "cooking",
            "video games",
            "ancient history",
            "arts"
        ],
        "age": 70
    },
    "Josh": {
        "interests": [
            "football",
            "arts",
            "video games",
            "ancient history",
            "gardening"
        ],
        "age": 11
    },
    "Mr Brown": {
        "interests": [
            "Japanese culture",
            "anime",
            "Rust"
        ],
        "age": 11
    },
    "Bread Black": {
        "interests": [
            "c++20",
            "template magic",
            "alchogol"
        ]
    }

}
